sendblue_api/__init__.py
sendblue_api/_base_client.py
sendblue_api/_client.py
sendblue_api/_compat.py
sendblue_api/_constants.py
sendblue_api/_exceptions.py
sendblue_api/_files.py
sendblue_api/_models.py
sendblue_api/_qs.py
sendblue_api/_resource.py
sendblue_api/_response.py
sendblue_api/_streaming.py
sendblue_api/_types.py
sendblue_api/_version.py
sendblue_api/py.typed
sendblue_api/_utils/__init__.py
sendblue_api/_utils/_compat.py
sendblue_api/_utils/_datetime_parse.py
sendblue_api/_utils/_logs.py
sendblue_api/_utils/_proxy.py
sendblue_api/_utils/_reflection.py
sendblue_api/_utils/_resources_proxy.py
sendblue_api/_utils/_streams.py
sendblue_api/_utils/_sync.py
sendblue_api/_utils/_transform.py
sendblue_api/_utils/_typing.py
sendblue_api/_utils/_utils.py
sendblue_api/lib/.keep
sendblue_api/resources/__init__.py
sendblue_api/resources/groups.py
sendblue_api/resources/lookups.py
sendblue_api/resources/media_objects.py
sendblue_api/resources/messages.py
sendblue_api/resources/typing_indicators.py
sendblue_api/resources/webhooks.py
sendblue_api/resources/contacts/__init__.py
sendblue_api/resources/contacts/bulk.py
sendblue_api/resources/contacts/contacts.py
sendblue_api/types/__init__.py
sendblue_api/types/contact.py
sendblue_api/types/contact_count_response.py
sendblue_api/types/contact_create_params.py
sendblue_api/types/contact_create_response.py
sendblue_api/types/contact_delete_response.py
sendblue_api/types/contact_list_params.py
sendblue_api/types/contact_list_response.py
sendblue_api/types/contact_retrieve_response.py
sendblue_api/types/contact_update_params.py
sendblue_api/types/contact_update_response.py
sendblue_api/types/contact_verify_params.py
sendblue_api/types/contact_verify_response.py
sendblue_api/types/group_modify_params.py
sendblue_api/types/group_modify_response.py
sendblue_api/types/group_send_message_params.py
sendblue_api/types/lookup_lookup_number_params.py
sendblue_api/types/lookup_lookup_number_response.py
sendblue-1.3.0.dist-info/METADATA
sendblue-1.3.0.dist-info/WHEEL
sendblue-1.3.0.dist-info/licenses/LICENSE
sendblue-1.3.0.dist-info/RECORD
